oc_ocdm/__init__.py
oc_ocdm/abstract_entity.py
oc_ocdm/abstract_set.py
oc_ocdm/counter_handler/__init__.py
oc_ocdm/counter_handler/counter_handler.py
oc_ocdm/counter_handler/filesystem_counter_handler.py
oc_ocdm/counter_handler/in_memory_counter_handler.py
oc_ocdm/counter_handler/redis_counter_handler.py
oc_ocdm/counter_handler/sqlite_counter_handler.py
oc_ocdm/decorators.py
oc_ocdm/graph/__init__.py
oc_ocdm/graph/entities/__init__.py
oc_ocdm/graph/entities/bibliographic/__init__.py
oc_ocdm/graph/entities/bibliographic/agent_role.py
oc_ocdm/graph/entities/bibliographic/bibliographic_reference.py
oc_ocdm/graph/entities/bibliographic/bibliographic_resource.py
oc_ocdm/graph/entities/bibliographic/citation.py
oc_ocdm/graph/entities/bibliographic/discourse_element.py
oc_ocdm/graph/entities/bibliographic/pointer_list.py
oc_ocdm/graph/entities/bibliographic/reference_annotation.py
oc_ocdm/graph/entities/bibliographic/reference_pointer.py
oc_ocdm/graph/entities/bibliographic/resource_embodiment.py
oc_ocdm/graph/entities/bibliographic/responsible_agent.py
oc_ocdm/graph/entities/bibliographic_entity.py
oc_ocdm/graph/entities/identifier.py
oc_ocdm/graph/graph_entity.py
oc_ocdm/graph/graph_set.py
oc_ocdm/metadata/__init__.py
oc_ocdm/metadata/entities/__init__.py
oc_ocdm/metadata/entities/dataset.py
oc_ocdm/metadata/entities/distribution.py
oc_ocdm/metadata/metadata_entity.py
oc_ocdm/metadata/metadata_set.py
oc_ocdm/prov/__init__.py
oc_ocdm/prov/entities/__init__.py
oc_ocdm/prov/entities/snapshot_entity.py
oc_ocdm/prov/prov_entity.py
oc_ocdm/prov/prov_set.py
oc_ocdm/reader.py
oc_ocdm/resources/__init__.py
oc_ocdm/resources/querymap.txt
oc_ocdm/resources/shacle.ttl
oc_ocdm/resources/shexc.txt
oc_ocdm/resources/shexc_closed.txt
oc_ocdm/storer.py
oc_ocdm/support/__init__.py
oc_ocdm/support/query_utils.py
oc_ocdm/support/reporter.py
oc_ocdm/support/support.py
oc_ocdm-9.4.3.dist-info/METADATA
oc_ocdm-9.4.3.dist-info/WHEEL
oc_ocdm-9.4.3.dist-info/licenses/LICENSE.md
oc_ocdm-9.4.3.dist-info/RECORD
