Metadata-Version: 2.4
Name: oc_ocdm
Version: 9.4.3
Summary: Object mapping library for manipulating RDF graphs that are compliant with the OpenCitations datamodel.
License: ISC
License-File: LICENSE.md
Keywords: opencitations,openscience,datamodel,mapping
Author: Silvio Peroni
Author-email: essepuntato@gmail.com
Requires-Python: >=3.10,<3.14
Classifier: Intended Audience :: Developers
Classifier: Intended Audience :: Science/Research
Classifier: License :: OSI Approved
Classifier: License :: OSI Approved :: ISC License (ISCL)
Classifier: Natural Language :: English
Classifier: Operating System :: OS Independent
Classifier: Programming Language :: Python
Classifier: Programming Language :: Python :: 3
Classifier: Programming Language :: Python :: 3.10
Classifier: Programming Language :: Python :: 3.11
Classifier: Programming Language :: Python :: 3.12
Classifier: Programming Language :: Python :: 3.13
Classifier: Topic :: Database
Classifier: Topic :: Software Development :: Libraries :: Python Modules
Classifier: Topic :: System :: Archiving
Classifier: Typing :: Typed
Requires-Dist: filelock (>=3.6.0,<4.0.0)
Requires-Dist: pyshacl (>=0.30.1,<0.31.0)
Requires-Dist: rdflib (>=7.4.0,<8.0.0)
Requires-Dist: redis (>=4.5.5,<8.0.0)
Requires-Dist: sparqlite (>=1.0.0,<2.0.0)
Requires-Dist: tqdm (>=4.67.1,<5.0.0)
Project-URL: Documentation, https://oc-ocdm.readthedocs.io
Project-URL: Homepage, https://opencitations.net
Project-URL: Repository, https://github.com/opencitations/oc_ocdm
